mqttd/__init__.py
mqttd/app.py
mqttd/decorators.py
mqttd/ngtcp2_bindings.py
mqttd/ngtcp2_tls_bindings.py
mqttd/properties.py
mqttd/protocol.py
mqttd/protocol_v5.py
mqttd/reason_codes.py
mqttd/session.py
mqttd/thread_safe.py
mqttd/transport_quic.py
mqttd/transport_quic_ngtcp2.py
mqttd/transport_quic_pure.py
mqttd/types.py
mqttd-0.3.1.dist-info/licenses/LICENSE
mqttd-0.3.1.dist-info/METADATA
mqttd-0.3.1.dist-info/WHEEL
mqttd-0.3.1.dist-info/top_level.txt
mqttd-0.3.1.dist-info/RECORD
