Metadata-Version: 2.4
Name: mqttd
Version: 0.3.1
Summary: FastAPI-like MQTT/MQTTS server for Python, compatible with libcurl clients
Home-page: https://github.com/arusatech/mqttd
Author: Yakub Mohammad
Author-email: Yakub Mohammad <yakub@arusatech.com>
License: MIT
Project-URL: Homepage, https://github.com/arusatech/mqttd
Project-URL: Documentation, https://github.com/arusatech/mqttd#readme
Project-URL: Repository, https://github.com/arusatech/mqttd
Project-URL: Bug Tracker, https://github.com/arusatech/mqttd/issues
Keywords: mqtt,mqtts,mqtt5,server,broker,fastapi,libcurl,quic,http3
Classifier: Development Status :: 4 - Beta
Classifier: Intended Audience :: Developers
Classifier: License :: OSI Approved :: MIT License
Classifier: Programming Language :: Python :: 3
Classifier: Programming Language :: Python :: 3.7
Classifier: Programming Language :: Python :: 3.8
Classifier: Programming Language :: Python :: 3.9
Classifier: Programming Language :: Python :: 3.10
Classifier: Programming Language :: Python :: 3.11
Classifier: Programming Language :: Python :: 3.12
Classifier: Programming Language :: Python :: 3.13
Classifier: Programming Language :: Python :: 3.14
Classifier: Topic :: Communications
Classifier: Topic :: Internet
Classifier: Topic :: Software Development :: Libraries :: Python Modules
Classifier: Topic :: System :: Networking
Requires-Python: >=3.7
License-File: LICENSE
Provides-Extra: redis
Requires-Dist: redis>=5.0.0; extra == "redis"
Provides-Extra: quic
Requires-Dist: aioquic>=0.9.20; extra == "quic"
Provides-Extra: dev
Requires-Dist: pytest>=6.0; extra == "dev"
Requires-Dist: pytest-asyncio>=0.18.0; extra == "dev"
Requires-Dist: black>=21.0; extra == "dev"
Requires-Dist: mypy>=0.900; extra == "dev"
Provides-Extra: all
Requires-Dist: redis>=5.0.0; extra == "all"
Requires-Dist: aioquic>=0.9.20; extra == "all"
Dynamic: author
Dynamic: home-page
Dynamic: license-file
Dynamic: requires-python
